<?xml version="1.0" encoding="utf-8"?>
<!DOCTYPE hibernate-mapping PUBLIC "-//Hibernate/Hibernate Mapping DTD 3.0//EN"
"http://hibernate.sourceforge.net/hibernate-mapping-3.0.dtd">
<!-- 
    Mapping file autogenerated by MyEclipse Persistence Tools
-->
<hibernate-mapping>
    <class name="model.notice.entity.NoticeWorkorder" table="NOTICE_WORKORDER" >
        <id name="worksheetWorkorderId" type="java.lang.String">
            <column name="WORKSHEET_WORKORDER_ID" length="20" />
            <generator class="com.trustel.id.UnIdGeneratorByDate" />
        </id>
        <property name="workorderCode" type="java.lang.String">
            <column name="WORKORDER_CODE" length="50" />
        </property>
        <property name="applyCompanyId" type="java.lang.String">
            <column name="APPLY_COMPANY_ID" length="20" />
        </property>
        <property name="applyCompany" type="java.lang.String">
            <column name="APPLY_COMPANY" length="100" />
        </property>
        <property name="applyUserId" type="java.lang.String">
            <column name="APPLY_USER_ID" length="20" />
        </property>
        <property name="applyUserName" type="java.lang.String">
            <column name="APPLY_USER_NAME" length="20" />
        </property>
        <property name="launchTime" type="java.util.Date">
            <column name="LAUNCH_TIME" length="7" />
        </property>
        <property name="workorderType" type="java.lang.String">
            <column name="WORKORDER_TYPE" length="8" />
        </property>
        <property name="planBeginTime" type="java.util.Date">
            <column name="PLAN_BEGIN_TIME" length="7" />
        </property>
        <property name="planEndTime" type="java.util.Date">
            <column name="PLAN_END_TIME" length="7" />
        </property>
        <property name="applyTitle" type="java.lang.String">
            <column name="APPLY_TITLE" length="2000" />
        </property>
        <property name="emergencyDegree" type="java.lang.String">
            <column name="EMERGENCY_DEGREE" length="1" />
        </property>
        <property name="applyDetail" type="java.lang.String">
            <column name="APPLY_DETAIL" length="4000" />
        </property>
        <property name="schemeInfo" type="java.lang.String">
            <column name="SCHEME_INFO" length="2000" />
        </property>
        <property name="schemeTimerange" type="java.lang.String">
            <column name="SCHEME_TIMERANGE" length="2000" />
        </property>
        <property name="schemeRisk" type="java.lang.String">
            <column name="SCHEME_RISK" length="2000" />
        </property>
        
        <property name="finishTime" type="java.util.Date">
            <column name="FINISH_TIME"   />
        </property>
        <property name="finishResult" type="java.lang.String">
            <column name="FINISH_RESULT" length="8" />
        </property>
        <property name="finishDescription" type="java.lang.String">
            <column name="FINISH_DESCRIPTION" length="2000" />
        </property>
        
        <property name="wtStatus" type="java.lang.String">
            <column name="WT_STATUS" length="100" />
        </property>
        <property name="draftFlag" type="java.lang.String">
            <column name="DRAFT_FLAG" length="1" />
        </property>
        <property name="flowType" type="java.lang.Integer">
            <column name="FLOW_TYPE"  precision="2" scale="0"  />
        </property>
        
<!-- 评分 -->
         <property name="repairSpeed" type="java.lang.String">
            <column name="REPAIR_SPEED" length="10" />
        </property>
         <property name="repairMass" type="java.lang.String">
            <column name="REPAIR_MASS" length="10" />
        </property>
         <property name="commentWords" type="java.lang.String">
            <column name="COMMENT_WORDS" length="1000" />
        </property>
        
         <property name="actorName" type="java.lang.String">
            <column name="ACTOR_NAME"   />
        </property>
         <property name="actorId" type="java.lang.String">
            <column name="ACTOR_ID"   />
        </property>
        
         <property name="flowChart" type="java.lang.String">
            <column name="FLOW_CHART"   />
        </property>
        
         <property name="organizationId" type="java.lang.String">
            <column name="ORGANIZATION_ID" length="20" />
         </property>
        
         <property name="organizationName" type="java.lang.String">
            <column name="ORGANIZATION_Name" length="50" />
         </property>
         
          <property name="isFangAnxinxi" type="java.lang.String">
            <column name="IS_FANG_ANXINXI"   />
        </property>
    </class>
</hibernate-mapping>
